mwparallelparser/__init__.py
mwparallelparser/exceptions.py
mwparallelparser/handler.py
mwparallelparser/lexer.py
mwparallelparser/mode_bind
mwparallelparser/parser.py
mwparallelparser/rlexer.py
mwparallelparser/tag.py
mwparallelparser/tokens
mwparallelparser-0.1.7.dist-info/LICENCE
mwparallelparser-0.1.7.dist-info/METADATA
mwparallelparser-0.1.7.dist-info/WHEEL
mwparallelparser-0.1.7.dist-info/top_level.txt
mwparallelparser-0.1.7.dist-info/RECORD
