Metadata-Version: 2.1
Name: mwparallelparser
Version: 0.1.7
Summary: A MediaWiki syntax parser that uses parallel markup approach
Home-page: https://github.com/solewniczak/mwparallelparser
Author: Szymon Olewniczak
Author-email: szyolewn@pg.edu.pl
License: UNKNOWN
Project-URL: Bug Tracker, https://github.com/solewniczak/mwparallelparser/issues
Platform: UNKNOWN
Classifier: Programming Language :: Python :: 3
Classifier: License :: OSI Approved :: MIT License
Classifier: Operating System :: OS Independent
Requires-Python: >=3.8
License-File: LICENCE
